{"ProId":"pro0427267708","ProName":"\u8702\u4e4b\u5de2\u8702\u5de2\u7d20","ProTitle":"\u8702\u4e4b\u5de2\u8702\u5de2\u7d20\u5929\u7136\u6b63\u54c1\u91ce\u751f\u8001\u8702\u5de2\u871c\u6b63\u5b97\u519c\u5bb6\u8702\u871c\u4e70\u4e94\u9001\u4e00500g","ProSubtitle":"3\u74f6\u4e00\u5468\u671f \u4e705\u90011 \u70ed\u95004\u4e07\u4ef6 \u54c1\u724c\u4fdd\u8bc1","IsShelves":"1","FreightRemarks":null,"Remarks":"","KeyWord":"\u8702\u5de2\u7d20","ClassType":"37","ClassName":"\u8702\u5de2\u7d20","IsUseConpon":"0","ProContent":"&lt;p&gt;&lt;img src=&quot;https:\/\/img.alicdn.com\/imgextra\/i2\/756883827\/TB26.pUepXXXXXLXXXXXXXXXXXX-756883827.jpg&quot; align=&quot;absmiddle&quot; class=&quot;img-ks-lazyload&quot; style=&quot;margin: 0px; padding: 0px; border: 0px; animation: ks-fadeIn 350ms linear 0ms 1 normal both; opacity: 1; vertical-align: top; float: none; color: rgb(64, 64, 64); font-family: tahoma, arial, \u5b8b\u4f53, sans-serif; font-size: 14px; line-height: 19.6px; white-space: normal; background-color: rgb(255, 255, 255);&quot;\/&gt;&lt;img src=&quot;https:\/\/img.alicdn.com\/imgextra\/i1\/756883827\/TB2epuscVXXXXavXpXXXXXXXXXX_!!756883827.jpg&quot; align=&quot;absmiddle&quot; class=&quot;img-ks-lazyload&quot; style=&quot;margin: 0px; padding: 0px; border: 0px; animation: ks-fadeIn 350ms linear 0ms 1 normal both; opacity: 1; vertical-align: top; float: none; color: rgb(64, 64, 64); font-family: tahoma, arial, \u5b8b\u4f53, sans-serif; font-size: 14px; line-height: 19.6px; white-space: normal; background-color: rgb(255, 255, 255);&quot;\/&gt;&lt;img src=&quot;https:\/\/img.alicdn.com\/imgextra\/i2\/756883827\/TB2wxiqcVXXXXaSXpXXXXXXXXXX_!!756883827.jpg&quot; align=&quot;absmiddle&quot; class=&quot;img-ks-lazyload&quot; style=&quot;margin: 0px; padding: 0px; border: 0px; animation: ks-fadeIn 350ms linear 0ms 1 normal both; opacity: 1; vertical-align: top; float: none; color: rgb(64, 64, 64); font-family: tahoma, arial, \u5b8b\u4f53, sans-serif; font-size: 14px; line-height: 19.6px; white-space: normal; background-color: rgb(255, 255, 255);&quot;\/&gt;&lt;img src=&quot;https:\/\/img.alicdn.com\/imgextra\/i3\/756883827\/TB2MhVIepXXXXcwXXXXXXXXXXXX-756883827.jpg&quot; align=&quot;absmiddle&quot; class=&quot;img-ks-lazyload&quot; style=&quot;margin: 0px; padding: 0px; border: 0px; animation: ks-fadeIn 350ms linear 0ms 1 normal both; opacity: 1; vertical-align: top; float: none; color: rgb(64, 64, 64); font-family: tahoma, arial, \u5b8b\u4f53, sans-serif; font-size: 14px; line-height: 19.6px; white-space: normal; background-color: rgb(255, 255, 255);&quot;\/&gt;&lt;img src=&quot;https:\/\/img.alicdn.com\/imgextra\/i2\/756883827\/TB2bywDcFXXXXbFXXXXXXXXXXXX_!!756883827.jpg&quot; align=&quot;absmiddle&quot; class=&quot;img-ks-lazyload&quot; style=&quot;margin: 0px; padding: 0px; border: 0px; animation: ks-fadeIn 350ms linear 0ms 1 normal both; opacity: 1; vertical-align: top; float: none; color: rgb(64, 64, 64); font-family: tahoma, arial, \u5b8b\u4f53, sans-serif; font-size: 14px; line-height: 19.6px; white-space: normal; background-color: rgb(255, 255, 255);&quot;\/&gt;&lt;img src=&quot;https:\/\/img.alicdn.com\/imgextra\/i2\/756883827\/TB2YlwscFXXXXbXXpXXXXXXXXXX_!!756883827.jpg&quot; align=&quot;absmiddle&quot; class=&quot;img-ks-lazyload&quot; style=&quot;margin: 0px; padding: 0px; border: 0px; animation: ks-fadeIn 350ms linear 0ms 1 normal both; opacity: 1; vertical-align: top; float: none; color: rgb(64, 64, 64); font-family: tahoma, arial, \u5b8b\u4f53, sans-serif; font-size: 14px; line-height: 19.6px; white-space: normal; background-color: rgb(255, 255, 255);&quot;\/&gt;&lt;img src=&quot;https:\/\/img.alicdn.com\/imgextra\/i1\/756883827\/TB2mbEKcFXXXXXQXXXXXXXXXXXX_!!756883827.jpg&quot; align=&quot;absmiddle&quot; class=&quot;img-ks-lazyload&quot; style=&quot;margin: 0px; padding: 0px; border: 0px; animation: ks-fadeIn 350ms linear 0ms 1 normal both; opacity: 1; vertical-align: top; float: none; color: rgb(64, 64, 64); font-family: tahoma, arial, \u5b8b\u4f53, sans-serif; font-size: 14px; line-height: 19.6px; white-space: normal; background-color: rgb(255, 255, 255);&quot;\/&gt;&lt;img src=&quot;https:\/\/img.alicdn.com\/imgextra\/i1\/756883827\/TB2OTwGcFXXXXaVXXXXXXXXXXXX_!!756883827.jpg&quot; align=&quot;absmiddle&quot; class=&quot;img-ks-lazyload&quot; style=&quot;margin: 0px; padding: 0px; border: 0px; animation: ks-fadeIn 350ms linear 0ms 1 normal both; opacity: 1; vertical-align: top; float: none; color: rgb(64, 64, 64); font-family: tahoma, arial, \u5b8b\u4f53, sans-serif; font-size: 14px; line-height: 19.6px; white-space: normal; background-color: rgb(255, 255, 255);&quot;\/&gt;&lt;img src=&quot;https:\/\/img.alicdn.com\/imgextra\/i3\/756883827\/TB2p1pxcVXXXXcCXXXXXXXXXXXX_!!756883827.jpg&quot; align=&quot;absmiddle&quot; class=&quot;img-ks-lazyload&quot; style=&quot;margin: 0px; padding: 0px; border: 0px; animation: ks-fadeIn 350ms linear 0ms 1 normal both; opacity: 1; vertical-align: top; float: none; color: rgb(64, 64, 64); font-family: tahoma, arial, \u5b8b\u4f53, sans-serif; font-size: 14px; line-height: 19.6px; white-space: normal; background-color: rgb(255, 255, 255);&quot;\/&gt;&lt;img src=&quot;https:\/\/img.alicdn.com\/imgextra\/i2\/756883827\/TB2WPNLcVXXXXXSXXXXXXXXXXXX_!!756883827.jpg&quot; align=&quot;absmiddle&quot; class=&quot;img-ks-lazyload&quot; style=&quot;margin: 0px; padding: 0px; border: 0px; animation: ks-fadeIn 350ms linear 0ms 1 normal both; opacity: 1; vertical-align: top; float: none; color: rgb(64, 64, 64); font-family: tahoma, arial, \u5b8b\u4f53, sans-serif; font-size: 14px; line-height: 19.6px; white-space: normal; background-color: rgb(255, 255, 255);&quot;\/&gt;&lt;\/p&gt;","LastUpdateDate":"2016-04-12 16:53:04","ProLogoImg":"\/Upload\/Uoloads\/2016-04-12\/570c59d9c5f67.jpg","Cut":"0","Cut2":"0","PriceRange":"1.00","Price":"60","Cut3":"0","ShelvesDate":null,"ProNumber":"6923986040393","Barcode":"6923986040393","Weight":500,"EmpCut":"0","imgs":["\/Upload\/Uoloads\/2016-04-12\/570c59e5ede48.jpg","\/Upload\/Uoloads\/2016-04-12\/570c59e5f0c0f.jpg","\/Upload\/Uoloads\/2016-04-12\/570c59e62e34c.jpg","\/Upload\/Uoloads\/2016-04-12\/570c59e704038.jpg","\/Upload\/Uoloads\/2016-04-12\/570c59ea0a7ab.jpg"],"token":"rhbnja145862596121","ProductList":null,"attrs":{"\u89c4\u683c_20":null}}