{"ProId":"pro6060151845","ProName":"\u5fbd\u8bb0\u9e21\u86cb\u5c0f\u9ebb\u82b1\u96f6\u98df\u5c0f\u5403\u591a\u53e3\u5473\u5c0f\u9ebb\u82b1\u6563\u88c5\u7cd5\u70b9228g","ProTitle":"\u5fbd\u8bb0\u9e21\u86cb\u5c0f\u9ebb\u82b1\u96f6\u98df\u5c0f\u5403\u591a\u53e3\u5473\u5c0f\u9ebb\u82b1\u6563\u88c5\u7cd5\u70b9228g","ProSubtitle":"","FreightRemarks":"","Remarks":"","KeyWord":"","IsUseConpon":null,"IsShelves":1,"ClassType":"1046","ClassName":null,"ProContent":"&lt;p&gt;&lt;img src=&quot;https:\/\/www.huijistore.com\/web\/php\/upload\/image\/20170922\/1506060149209650.jpg&quot; title=&quot;1506060149209650.jpg&quot; alt=&quot;\u5c0f\u9ebb\u82b1.jpg&quot;\/&gt;&lt;\/p&gt;","ProLogoImg":"\/logo59c4a763a1c30.jpeg","Cut":"0","Cut2":0,"PriceRange":"10.9","Price":null,"Cut3":0,"ShelvesDate":null,"ProNumber":"","Barcode":"","Weight":228,"EmpCut":null,"IsUseScore":"0","Score":"","Iszp":null,"token":"rhbnja145862596121","imgs":["\/logo59c4a76d26c72.jpeg"],"ProductList":{"pro6060151845_1":{"ProIdCard":"pro6060151845_1","ProSpec1":"\u9ed1\u829d\u9ebb\u5473","ProSpec2":" ","ProSpec3":" ","ProSpec4":" ","ProSpec5":" ","ProIdInputCard":"561651","Price":"10.9","ProId":"pro6060151845","EmpCut":null,"Iszp":null,"IsUseScore":"0","Score":"","token":"rhbnja145862596121","Count":null,"InputCode":"1654165","CosPrice":"9"},"pro6060151845_2":{"ProIdCard":"pro6060151845_2","ProSpec1":"\u9999\u8471\u5473","ProSpec2":" ","ProSpec3":" ","ProSpec4":" ","ProSpec5":" ","ProIdInputCard":"654165","Price":"10.9","ProId":"pro6060151845","EmpCut":null,"Iszp":null,"IsUseScore":"0","Score":"","token":"rhbnja145862596121","Count":null,"InputCode":"4131","CosPrice":"9"},"pro6060151845_3":{"ProIdCard":"pro6060151845_3","ProSpec1":"\u539f\u9999\u5473","ProSpec2":" ","ProSpec3":" ","ProSpec4":" ","ProSpec5":" ","ProIdInputCard":"2+6556+","Price":"10.9","ProId":"pro6060151845","EmpCut":null,"Iszp":null,"IsUseScore":"0","Score":"","token":"rhbnja145862596121","Count":null,"InputCode":"123132","CosPrice":"9"}}}